cv2multizoom/LICENSE
cv2multizoom/README.MD
cv2multizoom/__init__.py
cv2multizoom/requirements.txt
cv2multizoom/thirdparty.json
cv2multizoom-0.10.dist-info/LICENSE.rst
cv2multizoom-0.10.dist-info/METADATA
cv2multizoom-0.10.dist-info/WHEEL
cv2multizoom-0.10.dist-info/top_level.txt
cv2multizoom-0.10.dist-info/RECORD
