Metadata-Version: 2.1
Name: cv2multizoom
Version: 0.10
Summary: Fast multiple zooms on a picture using cv2 and ffmpeg
Home-page: https://github.com/hansalemaos/cv2multizoom
Author: Johannes Fischer
Author-email: <aulasparticularesdealemaosp@gmail.com>
License: MIT
Keywords: zoom,ffmpeg,cv2
Classifier: Development Status :: 4 - Beta
Classifier: Programming Language :: Python :: 3 :: Only
Classifier: Programming Language :: Python :: 3.9
Classifier: Topic :: Scientific/Engineering :: Visualization
Classifier: Topic :: Software Development :: Libraries :: Python Modules
Classifier: Topic :: Text Editors :: Text Processing
Classifier: Topic :: Text Processing :: General
Classifier: Topic :: Text Processing :: Indexing
Classifier: Topic :: Text Processing :: Filters
Classifier: Topic :: Utilities
License-File: LICENSE.rst
Requires-Dist: a-cv-imwrite-imread-plus
Requires-Dist: easy-symlink
Requires-Dist: opencv-python
Requires-Dist: regex
